hprint/__init__.py
hprint/dsutils.py
hprint/utils.py
hprint-2.1.2.dist-info/licenses/LICENSE
hprint-2.1.2.dist-info/METADATA
hprint-2.1.2.dist-info/WHEEL
hprint-2.1.2.dist-info/top_level.txt
hprint-2.1.2.dist-info/RECORD
